LICENSE
MANIFEST.in
README.rst
pyproject.toml
setup.py
tox.ini
docs/Makefile
docs/conf.py
docs/index.rst
docs/make.bat
licenses/APACHE2.rst
licenses/BSD2.rst
licenses/BSD3.rst
licenses/GPLv3.rst
licenses/README.rst
licenses/TEMPLATE_LICENSE.rst
shone/__init__.py
shone/version.py
shone.egg-info/PKG-INFO
shone.egg-info/SOURCES.txt
shone.egg-info/dependency_links.txt
shone.egg-info/not-zip-safe
shone.egg-info/requires.txt
shone.egg-info/top_level.txt
shone/data/README.rst
shone/tests/__init__.py