Metadata-Version: 2.1
Name: shone
Version: 0.0.0
Summary: Radiative transfer in JAX
Author-email: "Brett M. Morris, Jens Hoeijmakers" <morrisbrettm@gmail.com>
Project-URL: repository, https://github.com/bmorris3/shone
Requires-Python: >=3.11
License-File: LICENSE
Provides-Extra: test
Requires-Dist: pytest; extra == "test"
Requires-Dist: pytest-doctestplus; extra == "test"
Requires-Dist: pytest-cov; extra == "test"
Provides-Extra: docs
Requires-Dist: sphinx; extra == "docs"
Requires-Dist: sphinx-automodapi; extra == "docs"
